pycounts_tripartio/__init__.py
pycounts_tripartio/plotting.py
pycounts_tripartio/pycounts.py
pycounts_tripartio-0.1.0.dist-info/LICENSE
pycounts_tripartio-0.1.0.dist-info/METADATA
pycounts_tripartio-0.1.0.dist-info/WHEEL
pycounts_tripartio-0.1.0.dist-info/RECORD
